{
  "enableSearch": true,
  "pages": [
    {
      "src": "AboutUs.md",
      "title": "About Us",
      "headings": {
        "about-us": "About Us",
        "project-team": "Project team",
        "clement-oh": "Clement Oh",
        "wei-zhi": "Wei Zhi",
        "vincent-ng": "Vincent Ng",
        "arjun-kumanan": "Arjun Kumanan",
        "terence-wong": "Terence Wong"
      },
      "headingKeywords": {}
    },
    {
      "src": "Configuration.md",
      "title": "Configuration guide",
      "headings": {
        "configuration-guide": "Configuration guide"
      },
      "headingKeywords": {}
    },
    {
      "src": "DevOps.md",
      "title": "DevOps guide",
      "headings": {
        "devops-guide": "DevOps guide",
        "build-automation": "Build automation",
        "continuous-integration-ci": "Continuous integration (CI)",
        "code-coverage": "Code coverage",
        "repository-wide-checks": "Repository-wide checks",
        "making-a-release": "Making a release"
      },
      "headingKeywords": {}
    },
    {
      "src": "DeveloperGuide.md",
      "title": "Developer Guide",
      "headings": {
        "socialbook-developer-guide": "SocialBook Developer Guide",
        "acknowledgements": "Acknowledgements",
        "setting-up-getting-started": "Setting up, getting started",
        "design": "Design",
        "architecture": "Architecture",
        "ui-component": "UI component",
        "logic-component": "Logic component",
        "model-component": "Model component",
        "storage-component": "Storage component",
        "common-classes": "Common classes",
        "implementation": "Implementation",
        "proposed-undo-redo-feature": "[Proposed] Undo/redo feature",
        "proposed-data-archiving": "[Proposed] Data archiving",
        "documentation-logging-testing-configuration-dev-ops": "Documentation, logging, testing, configuration, dev-ops",
        "appendix-requirements": "Appendix: Requirements",
        "product-scope": "Product scope",
        "user-stories": "User stories",
        "use-cases": "Use cases",
        "non-functional-requirements": "Non-Functional Requirements",
        "glossary": "Glossary",
        "appendix-instructions-for-manual-testing": "Appendix: Instructions for manual testing",
        "launch-and-shutdown": "Launch and shutdown",
        "deleting-a-person": "Deleting a person",
        "saving-data": "Saving data"
      },
      "headingKeywords": {}
    },
    {
      "src": "Documentation.md",
      "title": "Documentation guide",
      "headings": {
        "documentation-guide": "Documentation Guide"
      },
      "headingKeywords": {}
    },
    {
      "src": "Logging.md",
      "title": "Logging guide",
      "headings": {
        "logging-guide": "Logging guide"
      },
      "headingKeywords": {}
    },
    {
      "src": "SettingUp.md",
      "title": "Setting up and getting started",
      "headings": {
        "setting-up-and-getting-started": "Setting up and getting started",
        "setting-up-the-project-in-your-computer": "Setting up the project in your computer",
        "before-writing-code": "Before writing code"
      },
      "headingKeywords": {}
    },
    {
      "src": "Testing.md",
      "title": "Testing guide",
      "headings": {
        "testing-guide": "Testing guide",
        "running-tests": "Running tests",
        "types-of-tests": "Types of tests"
      },
      "headingKeywords": {}
    },
    {
      "src": "UserGuide.md",
      "title": "User Guide",
      "headings": {
        "socialbook-user-guide": "SocialBook User Guide",
        "quick-start": "Quick start",
        "features": "Features",
        "viewing-help-help": "Viewing help: help",
        "adding-a-person-add": "Adding a person: add",
        "listing-all-persons-list": "Listing all persons: list",
        "editing-a-person-edit": "Editing a person: edit",
        "finding-persons-find": "Finding persons: find",
        "sorting-persons-sort": "Sorting persons: sort",
        "deleting-people-delete": "Deleting people: delete",
        "getting-the-parameters-of-these-people-get": "Getting the parameters of these people: get",
        "clearing-all-entries-clear": "Clearing all entries: clear",
        "adding-an-appointment-addappt": "Adding an appointment: addappt",
        "listing-all-appointments-listappt": "Listing all appointments: listappt",
        "editing-an-appointment-editappt": "Editing an appointment: editappt",
        "deleting-an-appointment-deleteappt": "Deleting an appointment: deleteappt",
        "displaying-overall-statistics-statistics": "Displaying overall statistics: statistics",
        "displaying-eligible-schemes-scheme": "Displaying eligible schemes: scheme",
        "adding-a-scheme-to-a-person-addscheme": "Adding a scheme to a person: addscheme",
        "viewing-schemes-attached-to-a-person-viewscheme": "Viewing schemes attached to a person: viewscheme",
        "delete-a-scheme-from-a-person-deletescheme": "Delete a scheme from a person: deletescheme",
        "archiving-a-person-archive": "Archiving a person: archive",
        "unarchiving-a-person-unarchive": "Unarchiving a person: unarchive",
        "undo-the-previous-command-undo": "Undo the previous command: undo",
        "exiting-the-program-exit": "Exiting the program: exit",
        "saving-the-data": "Saving the data",
        "editing-the-data-file": "Editing the data file",
        "going-through-entered-commands": "Going through entered commands",
        "calendar": "Calendar",
        "faq": "FAQ",
        "known-issues": "Known issues",
        "command-summary": "Command summary"
      },
      "headingKeywords": {}
    },
    {
      "src": "index.md",
      "title": "",
      "headings": {
        "socialbook": "SocialBook"
      },
      "headingKeywords": {}
    },
    {
      "src": "team/johndoe.md",
      "title": "John Doe's Project Portfolio Page",
      "headings": {
        "project-addressbook-level-3": "Project: AddressBook Level 3"
      },
      "headingKeywords": {}
    }
  ]
}
